Metadata-Version: 1.1
Name: arasel-test
Version: 0.1.2
Summary: Test Solution to TransfCustomer Lifetime Value for each customer in input CSV.
Home-page: https://github.com/bertucho/arasel_test
Author: Alberto Egido
Author-email: UNKNOWN
License: MIT license
Keywords: arasel_test
Platform: UNKNOWN
Classifier: Development Status :: 2 - Pre-Alpha
Classifier: Intended Audience :: Developers
Classifier: License :: OSI Approved :: MIT License
Classifier: Natural Language :: English
Classifier: Programming Language :: Python :: 2
Classifier: Programming Language :: Python :: 2.7
Classifier: Programming Language :: Python :: 3
Classifier: Programming Language :: Python :: 3.4
Classifier: Programming Language :: Python :: 3.5
Classifier: Programming Language :: Python :: 3.6
